.travis.yml
README.rst
setup.py
tox.ini
mr/__init__.py
mr.awsome.openvz.egg-info/PKG-INFO
mr.awsome.openvz.egg-info/SOURCES.txt
mr.awsome.openvz.egg-info/dependency_links.txt
mr.awsome.openvz.egg-info/entry_points.txt
mr.awsome.openvz.egg-info/namespace_packages.txt
mr.awsome.openvz.egg-info/not-zip-safe
mr.awsome.openvz.egg-info/requires.txt
mr.awsome.openvz.egg-info/top_level.txt
mr/awsome_openvz/__init__.py
mr/awsome_openvz/tests/__init__.py
mr/awsome_openvz/tests/test_openvz.py