Metadata-Version: 1.0
Name: mr.awsome.openvz
Version: 1.0b1
Summary: A plugin for mr.awsome providing support for OpenVZ containers.
Home-page: http://github.com/fschulze/mr.awsome.openvz
Author: Florian Schulze
Author-email: florian.schulze@gmx.net
License: UNKNOWN
Platform: UNKNOWN
